torchinstaller/__init__.py
torchinstaller/__main__.py
torchinstaller/__version__.py
torchinstaller/_parse.py
torchinstaller/_soup.py
torchinstaller/main.py
torchinstaller/utils.py
torchinstaller/config/commands.bak.toml
torchinstaller/config/commands.md
torchinstaller/config/commands.toml
torchinstaller-0.8.10.dist-info/METADATA
torchinstaller-0.8.10.dist-info/WHEEL
torchinstaller-0.8.10.dist-info/entry_points.txt
torchinstaller-0.8.10.dist-info/licenses/LICENSE
torchinstaller-0.8.10.dist-info/RECORD
