Metadata-Version: 2.3
Name: torchinstaller
Version: 0.8.10
Summary: Simple utility to install pytorch, pytorch-geometric and pytorch-lightning. Detects CUDA version automatically.
Project-URL: github, https://github.com/dk0d/torchinstaller.git
Author-email: Daniel Capecci <7775585+dk0d@users.noreply.github.com>
License: MIT
License-File: LICENSE
Requires-Python: <4.0,>=3.10
Requires-Dist: rich<14.0.0,>=13.3.3
Requires-Dist: tomlkit<1.0.0,>=0.11.7
Provides-Extra: sync
Requires-Dist: beautifulsoup4; extra == 'sync'
Requires-Dist: requests; extra == 'sync'
Requires-Dist: unmarkd; extra == 'sync'
